{
  "nearest": [
    {
      "symbol": "ATOMUSDT",
      "price": 1.81,
      "change_24h": -2.69,
      "nearest_type": "S",
      "nearest_price": 1.8287,
      "distance_pct": 1.03,
      "touches": 1
    },
    {
      "symbol": "TRXUSDT",
      "price": 0.2806,
      "change_24h": -0.95,
      "nearest_type": "S",
      "nearest_price": 0.27719499999999997,
      "distance_pct": 1.21,
      "touches": 2
    },
    {
      "symbol": "XRPUSDT",
      "price": 1.3607,
      "change_24h": -3.04,
      "nearest_type": "S",
      "nearest_price": 1.3416,
      "distance_pct": 1.4,
      "touches": 1
    },
    {
      "symbol": "HBARUSDT",
      "price": 0.0967,
      "change_24h": -2.52,
      "nearest_type": "R",
      "nearest_price": 0.09813,
      "distance_pct": 1.48,
      "touches": 1
    },
    {
      "symbol": "XLMUSDT",
      "price": 0.1509,
      "change_24h": -4.19,
      "nearest_type": "S",
      "nearest_price": 0.14722,
      "distance_pct": 2.44,
      "touches": 1
    },
    {
      "symbol": "INJUSDT",
      "price": 3.029,
      "change_24h": -3.26,
      "nearest_type": "S",
      "nearest_price": 2.955,
      "distance_pct": 2.44,
      "touches": 1
    },
    {
      "symbol": "LTCUSDT",
      "price": 54.78,
      "change_24h": -1.1,
      "nearest_type": "R",
      "nearest_price": 56.67,
      "distance_pct": 3.45,
      "touches": 1
    },
    {
      "symbol": "ADAUSDT",
      "price": 0.2635,
      "change_24h": -6.33,
      "nearest_type": "S",
      "nearest_price": 0.2534,
      "distance_pct": 3.83,
      "touches": 1
    },
    {
      "symbol": "ETHUSDT",
      "price": 1979.26,
      "change_24h": -3.7,
      "nearest_type": "S",
      "nearest_price": 1895.31,
      "distance_pct": 4.24,
      "touches": 1
    },
    {
      "symbol": "BTCUSDT",
      "price": 68222.63,
      "change_24h": -1.71,
      "nearest_type": "S",
      "nearest_price": 65088.0,
      "distance_pct": 4.59,
      "touches": 1
    }
  ],
  "total_coins": 33
}