{
  "nearest": [
    {
      "symbol": "XRPUSDT",
      "price": 1.3487,
      "change_24h": 0.05,
      "nearest_type": "S",
      "nearest_price": 1.3416,
      "distance_pct": 0.53,
      "touches": 1
    },
    {
      "symbol": "INJUSDT",
      "price": 3.002,
      "change_24h": -0.27,
      "nearest_type": "S",
      "nearest_price": 2.955,
      "distance_pct": 1.57,
      "touches": 1
    },
    {
      "symbol": "XLMUSDT",
      "price": 0.1496,
      "change_24h": -2.48,
      "nearest_type": "S",
      "nearest_price": 0.14722,
      "distance_pct": 1.59,
      "touches": 1
    },
    {
      "symbol": "ATOMUSDT",
      "price": 1.79,
      "change_24h": -0.11,
      "nearest_type": "S",
      "nearest_price": 1.8287,
      "distance_pct": 2.16,
      "touches": 1
    },
    {
      "symbol": "HBARUSDT",
      "price": 0.09499,
      "change_24h": -2.02,
      "nearest_type": "S",
      "nearest_price": 0.0926,
      "distance_pct": 2.52,
      "touches": 1
    },
    {
      "symbol": "BTCUSDT",
      "price": 66846.17,
      "change_24h": 1.18,
      "nearest_type": "S",
      "nearest_price": 65088.0,
      "distance_pct": 2.63,
      "touches": 1
    },
    {
      "symbol": "ETHUSDT",
      "price": 1957.69,
      "change_24h": 0.99,
      "nearest_type": "S",
      "nearest_price": 1895.31,
      "distance_pct": 3.19,
      "touches": 1
    },
    {
      "symbol": "DOTUSDT",
      "price": 1.486,
      "change_24h": -2.17,
      "nearest_type": "R",
      "nearest_price": 1.438,
      "distance_pct": 3.23,
      "touches": 1
    },
    {
      "symbol": "BCHUSDT",
      "price": 437.7,
      "change_24h": 0.21,
      "nearest_type": "S",
      "nearest_price": 422.77,
      "distance_pct": 3.41,
      "touches": 1
    },
    {
      "symbol": "ADAUSDT",
      "price": 0.2638,
      "change_24h": -2.8,
      "nearest_type": "S",
      "nearest_price": 0.2534,
      "distance_pct": 3.94,
      "touches": 1
    }
  ],
  "total_coins": 33
}