{
  "timestamp": "2026-03-02T11:50:58.204481+00:00",
  "coins": [
    {
      "symbol": "XRPUSDT",
      "score": 43,
      "direction": "SHORT",
      "price": 1.3533,
      "change_24h": -1.76
    },
    {
      "symbol": "HBARUSDT",
      "score": 42,
      "direction": "SHORT",
      "price": 0.09724,
      "change_24h": -1.9
    },
    {
      "symbol": "LINKUSDT",
      "score": 39,
      "direction": "LONG",
      "price": 8.71,
      "change_24h": -1.91
    },
    {
      "symbol": "SOLUSDT",
      "score": 37,
      "direction": "LONG",
      "price": 84.06,
      "change_24h": -1.33
    }
  ],
  "count": 4
}