{
  "timestamp": "2026-03-02T14:10:57.605365+00:00",
  "coins": [
    {
      "symbol": "BTCUSDT",
      "score": 51,
      "direction": "SHORT",
      "price": 65534.57,
      "change_24h": -2.16
    },
    {
      "symbol": "LINKUSDT",
      "score": 41,
      "direction": "SHORT",
      "price": 8.64,
      "change_24h": -4.11
    },
    {
      "symbol": "XRPUSDT",
      "score": 39,
      "direction": "LONG",
      "price": 1.3409,
      "change_24h": -3.68
    },
    {
      "symbol": "NEARUSDT",
      "score": 38,
      "direction": "SHORT",
      "price": 1.231,
      "change_24h": 4.86
    }
  ],
  "count": 4
}