{
  "timestamp": "2026-03-01T20:30:01.141095+00:00",
  "coins": [
    {
      "symbol": "BTCUSDT",
      "score": 47,
      "direction": "SHORT",
      "price": 65359.58,
      "change_24h": -2.15
    },
    {
      "symbol": "AAVEUSDT",
      "score": 44,
      "direction": "SHORT",
      "price": 111.43,
      "change_24h": -0.56
    },
    {
      "symbol": "XRPUSDT",
      "score": 44,
      "direction": "SHORT",
      "price": 1.344,
      "change_24h": -2.21
    },
    {
      "symbol": "APTUSDT",
      "score": 42,
      "direction": "SHORT",
      "price": 0.911,
      "change_24h": -3.9
    },
    {
      "symbol": "NEARUSDT",
      "score": 40,
      "direction": "SHORT",
      "price": 1.118,
      "change_24h": -1.93
    },
    {
      "symbol": "LINKUSDT",
      "score": 35,
      "direction": "SHORT",
      "price": 8.62,
      "change_24h": -1.94
    }
  ],
  "count": 6
}